modelctx/__init__.py
modelctx/cli.py
modelctx/exceptions.py
modelctx/backends/__init__.py
modelctx/backends/api.py
modelctx/backends/base.py
modelctx/backends/cloudstorage.py
modelctx/backends/database.py
modelctx/backends/email.py
modelctx/backends/filesystem.py
modelctx/backends/webscraper.py
modelctx/core/__init__.py
modelctx/core/backend_registry.py
modelctx/core/config.py
modelctx/core/config_generator.py
modelctx/core/dependency_manager.py
modelctx/core/documentation_generator.py
modelctx/core/generator.py
modelctx/core/project_structure.py
modelctx/core/script_generator.py
modelctx/core/templates.py
modelctx/core/test_generator.py
modelctx/templates/api/.env.jinja2
modelctx/templates/base/.env.jinja2
modelctx/templates/base/.gitignore.j2
modelctx/templates/base/API.md.j2
modelctx/templates/base/DEPLOYMENT.md.j2
modelctx/templates/base/README.md.j2
modelctx/templates/base/pyproject.toml.j2
modelctx/templates/base/server.py.j2
modelctx/templates/base/test_server.py.j2
modelctx/templates/cloudstorage/.env.jinja2
modelctx/templates/database/.env.jinja2
modelctx/templates/email/.env.jinja2
modelctx/templates/filesystem/.env.jinja2
modelctx/templates/webscraper/.env.jinja2
modelctx/utils/__init__.py
modelctx/utils/error_handling.py
modelctx/utils/logging.py
modelctx/utils/security.py
modelctx/utils/validation.py
modelcontextkit-0.1.2.dist-info/METADATA
modelcontextkit-0.1.2.dist-info/WHEEL
modelcontextkit-0.1.2.dist-info/entry_points.txt
modelcontextkit-0.1.2.dist-info/top_level.txt
modelcontextkit-0.1.2.dist-info/RECORD
