Metadata-Version: 2.4
Name: modelcontextkit
Version: 0.1.2
Summary: A comprehensive CLI tool for rapidly creating, configuring, and deploying Model Context Protocol (MCP) servers
Author-email: Ersin Koç <ersinkoc@gmail.com>
Project-URL: Homepage, https://github.com/ModelContextKit/modelctx
Project-URL: Repository, https://github.com/ModelContextKit/modelctx
Project-URL: Documentation, https://github.com/ModelContextKit/modelctx/wiki
Project-URL: Bug Tracker, https://github.com/ModelContextKit/modelctx/issues
Keywords: mcp,model-context-protocol,cli,server,development
Classifier: Development Status :: 3 - Alpha
Classifier: Intended Audience :: Developers
Classifier: Topic :: Software Development :: Libraries :: Python Modules
Classifier: Programming Language :: Python :: 3
Classifier: Programming Language :: Python :: 3.8
Classifier: Programming Language :: Python :: 3.9
Classifier: Programming Language :: Python :: 3.10
Classifier: Programming Language :: Python :: 3.11
Classifier: Programming Language :: Python :: 3.12
Requires-Python: >=3.8
Requires-Dist: click>=8.0.0
Requires-Dist: rich>=12.0.0
Requires-Dist: pydantic>=2.0.0
Requires-Dist: pyyaml>=6.0.0
Requires-Dist: jinja2>=3.0.0
